<annotation verified="yes">
	<folder>Images</folder>
	<filename>IMG_20210817_165855.jpg</filename>
	<path>C:\Users\victo.SURFACEPRO-VICT\Downloads\Images\IMG_20210817_165855.jpg</path>
	<source>
		<database>Unknown</database>
	</source>
	<size>
		<width>4608</width>
		<height>2592</height>
		<depth>3</depth>
	</size>
	<segmented>0</segmented>
	<object>
		<name>Speed Limit 30</name>
		<pose>Unspecified</pose>
		<truncated>0</truncated>
		<difficult>0</difficult>
		<bndbox>
			<xmin>298</xmin>
			<ymin>234</ymin>
			<xmax>540</xmax>
			<ymax>455</ymax>
		</bndbox>
	</object>
	<object>
		<name>Speed Limit 50</name>
		<pose>Unspecified</pose>
		<truncated>0</truncated>
		<difficult>0</difficult>
		<bndbox>
			<xmin>761</xmin>
			<ymin>300</ymin>
			<xmax>1015</xmax>
			<ymax>549</ymax>
		</bndbox>
	</object>
	<object>
		<name>Prohibition Sign</name>
		<pose>Unspecified</pose>
		<truncated>0</truncated>
		<difficult>0</difficult>
		<bndbox>
			<xmin>1359</xmin>
			<ymin>287</ymin>
			<xmax>1663</xmax>
			<ymax>591</ymax>
		</bndbox>
	</object>
	<object>
		<name>Stop Sign</name>
		<pose>Unspecified</pose>
		<truncated>0</truncated>
		<difficult>0</difficult>
		<bndbox>
			<xmin>2766</xmin>
			<ymin>285</ymin>
			<xmax>3029</xmax>
			<ymax>553</ymax>
		</bndbox>
	</object>
	<object>
		<name>Traffic Light</name>
		<pose>Unspecified</pose>
		<truncated>0</truncated>
		<difficult>0</difficult>
		<bndbox>
			<xmin>3636</xmin>
			<ymin>32</ymin>
			<xmax>3866</xmax>
			<ymax>510</ymax>
		</bndbox>
	</object>
</annotation>
